{
	"name": "CosmosDbSqlApiCrewCollection",
	"properties": {
		"linkedServiceName": {
			"referenceName": "CosmosDbSQLAPIService",
			"type": "LinkedServiceReference"
		},
		"annotations": [],
		"type": "CosmosDbSqlApiCollection",
		"schema": {
			"type": "object",
			"properties": {
				"name": {
					"type": "string"
				},
				"surname": {
					"type": "string"
				},
				"pool": {
					"type": "string"
				},
				"rank": {
					"type": "string"
				},
				"offshore": {
					"type": "boolean"
				},
				"SBMer": {
					"type": "boolean"
				},
				"vesselName": {
					"type": "string"
				},
				"region": {
					"type": "integer"
				},
				"department": {
					"type": "string"
				}
			}
		},
		"typeProperties": {
			"collectionName": "crew_dw"
		}
	},
	"type": "Microsoft.DataFactory/factories/datasets"
}